cftime_rs-0.1.6.dist-info/METADATA
cftime_rs-0.1.6.dist-info/WHEEL
cftime_rs-0.1.6.dist-info/license_files/LICENSE
cftime_rs/cftime_rs.pyi
cftime_rs/py.typed
cftime_rs/tests/test_functions.py
cftime_rs/tests/__init__.py
cftime_rs/__init__.py
cftime_rs/cftime_rs.pyd
cftime_rs-0.1.6.dist-info/RECORD
