Metadata-Version: 2.1
Name: cftime-rs
Version: 0.1.6
Classifier: Programming Language :: Rust
Classifier: Programming Language :: Python :: Implementation :: CPython
Classifier: Programming Language :: Python :: Implementation :: PyPy
Requires-Dist: cftime-rs ; extra == 'dev'
Requires-Dist: pytest >=6.1.1 ; extra == 'dev'
Requires-Dist: pytest-cov >=2.10.1 ; extra == 'dev'
Requires-Dist: pytest-mock >=3.6.1 ; extra == 'dev'
Requires-Dist: coverage >=5.3 ; extra == 'dev'
Requires-Dist: sphinx >=4.5.0 ; extra == 'dev'
Requires-Dist: sphinx-autoapi ; extra == 'dev'
Requires-Dist: myst ; extra == 'dev'
Requires-Dist: myst-parser ; extra == 'dev'
Requires-Dist: sphinx_book_theme >=0.3.0 ; extra == 'dev'
Provides-Extra: dev
License-File: LICENSE
Summary: Rust implementation of cftime
Keywords: cftime,cf-conventions,climate,netcdf,meteorology
Author: Antoine Gibek
License: AGPL-3.0
Requires-Python: >=3.7
Project-URL: Source Code, https://github.com/antscloud/cftime-rs
